htm_pytorch/__init__.py
htm_pytorch/htm_pytorch.py
htm_pytorch-0.0.4.dist-info/LICENSE
htm_pytorch-0.0.4.dist-info/METADATA
htm_pytorch-0.0.4.dist-info/WHEEL
htm_pytorch-0.0.4.dist-info/top_level.txt
htm_pytorch-0.0.4.dist-info/RECORD
